{
 "task": "pan_meta_pri",
 "channel_set": "mut_cnv",
 "channels": [
  "mut",
  "cnv"
 ],
 "n_channels": 2,
 "marker_mode": "pathway",
 "gene_interaction": "reactome",
 "recursion_mode": "token",
 "pathway_attn_bias": false,
 "n_samples": 8893,
 "n_genes": 10333,
 "n_pathways": 1258,
 "n_classes": 32,
 "n_train": 6046,
 "n_test": 1779,
 "class_names": [
  "adrenocortical cancer",
  "bladder urothelial carcinoma",
  "brain lower grade glioma",
  "breast invasive carcinoma",
  "cervical & endocervical cancer",
  "cholangiocarcinoma",
  "colon adenocarcinoma",
  "diffuse large B-cell lymphoma",
  "esophageal carcinoma",
  "glioblastoma multiforme",
  "head & neck squamous cell carcinoma",
  "kidney chromophobe",
  "kidney clear cell carcinoma",
  "kidney papillary cell carcinoma",
  "liver hepatocellular carcinoma",
  "lung adenocarcinoma",
  "lung squamous cell carcinoma",
  "mesothelioma",
  "ovarian serous cystadenocarcinoma",
  "pancreatic adenocarcinoma",
  "pheochromocytoma & paraganglioma",
  "prostate adenocarcinoma",
  "rectum adenocarcinoma",
  "sarcoma",
  "skin cutaneous melanoma",
  "stomach adenocarcinoma",
  "testicular germ cell tumor",
  "thymoma",
  "thyroid carcinoma",
  "uterine carcinosarcoma",
  "uterine corpus endometrioid carcinoma",
  "uveal melanoma"
 ],
 "transformer_params": 132992,
 "total_params": 1482413,
 "mean_recursion_depth": 3.239122152328491,
 "compute_saving_ratio": 0.7203605492944118,
 "config": {
  "heads": [
   "pan_meta_pri"
  ],
  "cohorts": null,
  "n_hvg": null,
  "n_channels": 2,
  "batch_size": 32,
  "val_frac": 0.15,
  "test_frac": 0.15,
  "d_model": 128,
  "n_heads": 4,
  "d_ff": 256,
  "dropout": 0.1,
  "n_markers": 256,
  "marker_mode": "pathway",
  "pathway_pool": "mean",
  "compress_mode": "aggregate",
  "recursive_marker_refine": true,
  "peak_init": true,
  "anneal_markers": true,
  "recursion_depth": 4,
  "share_weights": true,
  "share_strategy": "cycle",
  "n_unique_blocks": null,
  "step_cache": false,
  "adaptive_depth": false,
  "marker_ffn": false,
  "recursion_mode": "token",
  "router_capacity": null,
  "router_alpha": 1.0,
  "router_temp": 1.0,
  "router_type": "linear",
  "router_z_coeff": 0.001,
  "router_balance_coeff": 0.1,
  "gene_interaction": "reactome",
  "interaction_knn": 16,
  "router_prior_beta": 1.0,
  "router_prior_anneal": true,
  "bio_graph_prop": false,
  "bio_prop_lambda_init": 0.3,
  "bio_prop_hops": 1,
  "bio_prior_gate": false,
  "bio_deconfound_pc": 0,
  "bio_precision": false,
  "bio_centrality": "eigcent",
  "bio_prior_learnable": false,
  "bio_beta_init": 0.5,
  "bio_depth_laplacian": 0.0,
  "bio_learned_graph": false,
  "bio_learned_rank": 16,
  "bio_learned_init": "random",
  "bio_learned_fuse": false,
  "bio_fuse_source": "coexpr",
  "aggnet_species": "human",
  "bio_learned_anchor": false,
  "bio_anchor_lambda": 0.5,
  "bio_anchor_floor": 0.0,
  "bio_anchor_rank": 16,
  "bio_anchor_source": "coexpr",
  "bio_init_scale": 0.05,
  "bio_init_rand": 0.005,
  "pathway_attn_bias": false,
  "pathway_attn_lambda": 2.0,
  "lambda_marker": 0.1,
  "gamma_diversity": 0.05,
  "beta_compression": 0.01,
  "lr": 0.0003,
  "weight_decay": 0.01,
  "epochs": 40,
  "patience": 8,
  "seed": 1,
  "device": "cuda"
 },
 "accuracy": 0.36031478358628444,
 "macro_f1": 0.3239692847087426,
 "val_macro_f1": 0.3185847834438387,
 "weighted_f1": 0.35131551306327585,
 "per_class": {
  "0": {
   "precision": 0.16,
   "recall": 0.2222222222222222,
   "f1-score": 0.18604651162790697,
   "support": 18.0
  },
  "1": {
   "precision": 0.20833333333333334,
   "recall": 0.12345679012345678,
   "f1-score": 0.15503875968992248,
   "support": 81.0
  },
  "2": {
   "precision": 0.5066666666666667,
   "recall": 0.37254901960784315,
   "f1-score": 0.4293785310734463,
   "support": 102.0
  },
  "3": {
   "precision": 0.47368421052631576,
   "recall": 0.17197452229299362,
   "f1-score": 0.2523364485981308,
   "support": 157.0
  },
  "4": {
   "precision": 0.22413793103448276,
   "recall": 0.23214285714285715,
   "f1-score": 0.22807017543859648,
   "support": 56.0
  },
  "5": {
   "precision": 0.0,
   "recall": 0.0,
   "f1-score": 0.0,
   "support": 7.0
  },
  "6": {
   "precision": 0.30303030303030304,
   "recall": 0.1724137931034483,
   "f1-score": 0.21978021978021978,
   "support": 58.0
  },
  "7": {
   "precision": 0.05,
   "recall": 0.2857142857142857,
   "f1-score": 0.0851063829787234,
   "support": 7.0
  },
  "8": {
   "precision": 0.15254237288135594,
   "recall": 0.24324324324324326,
   "f1-score": 0.1875,
   "support": 37.0
  },
  "9": {
   "precision": 0.36470588235294116,
   "recall": 0.5081967213114754,
   "f1-score": 0.4246575342465753,
   "support": 61.0
  },
  "10": {
   "precision": 0.27450980392156865,
   "recall": 0.14,
   "f1-score": 0.18543046357615894,
   "support": 100.0
  },
  "11": {
   "precision": 0.5,
   "recall": 0.7692307692307693,
   "f1-score": 0.6060606060606061,
   "support": 13.0
  },
  "12": {
   "precision": 0.4222222222222222,
   "recall": 0.5205479452054794,
   "f1-score": 0.4662576687116564,
   "support": 73.0
  },
  "13": {
   "precision": 0.5490196078431373,
   "recall": 0.5,
   "f1-score": 0.5233644859813084,
   "support": 56.0
  },
  "14": {
   "precision": 0.2692307692307692,
   "recall": 0.29577464788732394,
   "f1-score": 0.28187919463087246,
   "support": 71.0
  },
  "15": {
   "precision": 0.3220338983050847,
   "recall": 0.18627450980392157,
   "f1-score": 0.2360248447204969,
   "support": 102.0
  },
  "16": {
   "precision": 0.4793388429752066,
   "recall": 0.6041666666666666,
   "f1-score": 0.5345622119815668,
   "support": 96.0
  },
  "17": {
   "precision": 0.11764705882352941,
   "recall": 0.25,
   "f1-score": 0.16,
   "support": 16.0
  },
  "18": {
   "precision": 0.15625,
   "recall": 0.4166666666666667,
   "f1-score": 0.22727272727272727,
   "support": 12.0
  },
  "19": {
   "precision": 0.26666666666666666,
   "recall": 0.22857142857142856,
   "f1-score": 0.24615384615384617,
   "support": 35.0
  },
  "20": {
   "precision": 0.3333333333333333,
   "recall": 0.46875,
   "f1-score": 0.38961038961038963,
   "support": 32.0
  },
  "21": {
   "precision": 0.5802469135802469,
   "recall": 0.47959183673469385,
   "f1-score": 0.5251396648044693,
   "support": 98.0
  },
  "22": {
   "precision": 0.1509433962264151,
   "recall": 0.4444444444444444,
   "f1-score": 0.22535211267605634,
   "support": 18.0
  },
  "23": {
   "precision": 0.18518518518518517,
   "recall": 0.2127659574468085,
   "f1-score": 0.19801980198019803,
   "support": 47.0
  },
  "24": {
   "precision": 0.3855421686746988,
   "recall": 0.4444444444444444,
   "f1-score": 0.4129032258064516,
   "support": 72.0
  },
  "25": {
   "precision": 0.375,
   "recall": 0.10227272727272728,
   "f1-score": 0.16071428571428573,
   "support": 88.0
  },
  "26": {
   "precision": 0.5476190476190477,
   "recall": 0.7931034482758621,
   "f1-score": 0.647887323943662,
   "support": 29.0
  },
  "27": {
   "precision": 0.2,
   "recall": 0.16666666666666666,
   "f1-score": 0.18181818181818182,
   "support": 24.0
  },
  "28": {
   "precision": 0.5925925925925926,
   "recall": 0.8247422680412371,
   "f1-score": 0.6896551724137931,
   "support": 97.0
  },
  "29": {
   "precision": 0.06382978723404255,
   "recall": 0.2727272727272727,
   "f1-score": 0.10344827586206896,
   "support": 11.0
  },
  "30": {
   "precision": 0.45714285714285713,
   "recall": 0.5393258426966292,
   "f1-score": 0.4948453608247423,
   "support": 89.0
  },
  "31": {
   "precision": 0.6190476190476191,
   "recall": 0.8125,
   "f1-score": 0.7027027027027027,
   "support": 16.0
  },
  "accuracy": 0.36031478358628444,
  "macro avg": {
   "precision": 0.32157820220155064,
   "recall": 0.3688900311732771,
   "f1-score": 0.3239692847087426,
   "support": 1779.0
  },
  "weighted avg": {
   "precision": 0.3821956213451716,
   "recall": 0.36031478358628444,
   "f1-score": 0.35131551306327585,
   "support": 1779.0
  }
 }
}