{
 "task": "pan_meta_pri",
 "channel_set": "mut_cnv",
 "channels": [
  "mut",
  "cnv"
 ],
 "n_channels": 2,
 "marker_mode": "pathway",
 "gene_interaction": "reactome",
 "recursion_mode": "expert",
 "pathway_attn_bias": false,
 "n_samples": 8893,
 "n_genes": 10333,
 "n_pathways": 1258,
 "n_classes": 32,
 "n_train": 6046,
 "n_test": 1779,
 "class_names": [
  "adrenocortical cancer",
  "bladder urothelial carcinoma",
  "brain lower grade glioma",
  "breast invasive carcinoma",
  "cervical & endocervical cancer",
  "cholangiocarcinoma",
  "colon adenocarcinoma",
  "diffuse large B-cell lymphoma",
  "esophageal carcinoma",
  "glioblastoma multiforme",
  "head & neck squamous cell carcinoma",
  "kidney chromophobe",
  "kidney clear cell carcinoma",
  "kidney papillary cell carcinoma",
  "liver hepatocellular carcinoma",
  "lung adenocarcinoma",
  "lung squamous cell carcinoma",
  "mesothelioma",
  "ovarian serous cystadenocarcinoma",
  "pancreatic adenocarcinoma",
  "pheochromocytoma & paraganglioma",
  "prostate adenocarcinoma",
  "rectum adenocarcinoma",
  "sarcoma",
  "skin cutaneous melanoma",
  "stomach adenocarcinoma",
  "testicular germ cell tumor",
  "thymoma",
  "thyroid carcinoma",
  "uterine carcinosarcoma",
  "uterine corpus endometrioid carcinoma",
  "uveal melanoma"
 ],
 "transformer_params": 132864,
 "total_params": 1482285,
 "mean_recursion_depth": 2.2503974437713623,
 "compute_saving_ratio": 0.6290129783213939,
 "config": {
  "heads": [
   "pan_meta_pri"
  ],
  "cohorts": null,
  "n_hvg": null,
  "n_channels": 2,
  "batch_size": 32,
  "val_frac": 0.15,
  "test_frac": 0.15,
  "d_model": 128,
  "n_heads": 4,
  "d_ff": 256,
  "dropout": 0.1,
  "n_markers": 256,
  "marker_mode": "pathway",
  "pathway_pool": "mean",
  "compress_mode": "aggregate",
  "recursive_marker_refine": true,
  "peak_init": true,
  "anneal_markers": true,
  "recursion_depth": 3,
  "share_weights": true,
  "share_strategy": "cycle",
  "n_unique_blocks": null,
  "step_cache": false,
  "adaptive_depth": false,
  "marker_ffn": false,
  "recursion_mode": "expert",
  "router_capacity": null,
  "router_alpha": 1.0,
  "router_temp": 1.0,
  "router_type": "linear",
  "router_z_coeff": 0.001,
  "router_balance_coeff": 0.1,
  "gene_interaction": "reactome",
  "interaction_knn": 16,
  "router_prior_beta": 1.0,
  "router_prior_anneal": true,
  "bio_graph_prop": false,
  "bio_prop_lambda_init": 0.3,
  "bio_prop_hops": 1,
  "bio_prior_gate": false,
  "bio_deconfound_pc": 0,
  "bio_precision": false,
  "bio_centrality": "eigcent",
  "bio_prior_learnable": false,
  "bio_beta_init": 0.5,
  "bio_depth_laplacian": 0.0,
  "bio_learned_graph": false,
  "bio_learned_rank": 16,
  "bio_learned_init": "random",
  "bio_learned_fuse": false,
  "bio_fuse_source": "coexpr",
  "aggnet_species": "human",
  "bio_learned_anchor": false,
  "bio_anchor_lambda": 0.5,
  "bio_anchor_floor": 0.0,
  "bio_anchor_rank": 16,
  "bio_anchor_source": "coexpr",
  "bio_init_scale": 0.05,
  "bio_init_rand": 0.005,
  "pathway_attn_bias": false,
  "pathway_attn_lambda": 2.0,
  "lambda_marker": 0.1,
  "gamma_diversity": 0.05,
  "beta_compression": 0.01,
  "lr": 0.0003,
  "weight_decay": 0.01,
  "epochs": 40,
  "patience": 8,
  "seed": 2,
  "device": "cuda"
 },
 "accuracy": 0.4092186621697583,
 "macro_f1": 0.37209566146448914,
 "val_macro_f1": 0.34635058674408536,
 "weighted_f1": 0.4030808644228083,
 "per_class": {
  "0": {
   "precision": 0.36363636363636365,
   "recall": 0.4444444444444444,
   "f1-score": 0.4,
   "support": 18.0
  },
  "1": {
   "precision": 0.35135135135135137,
   "recall": 0.16049382716049382,
   "f1-score": 0.22033898305084745,
   "support": 81.0
  },
  "2": {
   "precision": 0.6363636363636364,
   "recall": 0.5490196078431373,
   "f1-score": 0.5894736842105263,
   "support": 102.0
  },
  "3": {
   "precision": 0.5,
   "recall": 0.2356687898089172,
   "f1-score": 0.3203463203463203,
   "support": 157.0
  },
  "4": {
   "precision": 0.21333333333333335,
   "recall": 0.2857142857142857,
   "f1-score": 0.24427480916030533,
   "support": 56.0
  },
  "5": {
   "precision": 0.12,
   "recall": 0.42857142857142855,
   "f1-score": 0.1875,
   "support": 7.0
  },
  "6": {
   "precision": 0.2972972972972973,
   "recall": 0.1896551724137931,
   "f1-score": 0.23157894736842105,
   "support": 58.0
  },
  "7": {
   "precision": 0.07142857142857142,
   "recall": 0.2857142857142857,
   "f1-score": 0.11428571428571428,
   "support": 7.0
  },
  "8": {
   "precision": 0.0945945945945946,
   "recall": 0.1891891891891892,
   "f1-score": 0.12612612612612611,
   "support": 37.0
  },
  "9": {
   "precision": 0.4722222222222222,
   "recall": 0.5573770491803278,
   "f1-score": 0.5112781954887218,
   "support": 61.0
  },
  "10": {
   "precision": 0.4,
   "recall": 0.16,
   "f1-score": 0.22857142857142856,
   "support": 100.0
  },
  "11": {
   "precision": 0.6875,
   "recall": 0.8461538461538461,
   "f1-score": 0.7586206896551724,
   "support": 13.0
  },
  "12": {
   "precision": 0.7105263157894737,
   "recall": 0.7397260273972602,
   "f1-score": 0.7248322147651006,
   "support": 73.0
  },
  "13": {
   "precision": 0.6274509803921569,
   "recall": 0.5714285714285714,
   "f1-score": 0.5981308411214953,
   "support": 56.0
  },
  "14": {
   "precision": 0.3466666666666667,
   "recall": 0.36619718309859156,
   "f1-score": 0.3561643835616438,
   "support": 71.0
  },
  "15": {
   "precision": 0.38461538461538464,
   "recall": 0.19607843137254902,
   "f1-score": 0.2597402597402597,
   "support": 102.0
  },
  "16": {
   "precision": 0.46308724832214765,
   "recall": 0.71875,
   "f1-score": 0.563265306122449,
   "support": 96.0
  },
  "17": {
   "precision": 0.18181818181818182,
   "recall": 0.25,
   "f1-score": 0.21052631578947367,
   "support": 16.0
  },
  "18": {
   "precision": 0.07894736842105263,
   "recall": 0.25,
   "f1-score": 0.12,
   "support": 12.0
  },
  "19": {
   "precision": 0.2647058823529412,
   "recall": 0.2571428571428571,
   "f1-score": 0.2608695652173913,
   "support": 35.0
  },
  "20": {
   "precision": 0.4772727272727273,
   "recall": 0.65625,
   "f1-score": 0.5526315789473685,
   "support": 32.0
  },
  "21": {
   "precision": 0.5882352941176471,
   "recall": 0.40816326530612246,
   "f1-score": 0.4819277108433735,
   "support": 98.0
  },
  "22": {
   "precision": 0.13043478260869565,
   "recall": 0.3333333333333333,
   "f1-score": 0.1875,
   "support": 18.0
  },
  "23": {
   "precision": 0.18461538461538463,
   "recall": 0.2553191489361702,
   "f1-score": 0.21428571428571427,
   "support": 47.0
  },
  "24": {
   "precision": 0.5487804878048781,
   "recall": 0.625,
   "f1-score": 0.5844155844155844,
   "support": 72.0
  },
  "25": {
   "precision": 0.5,
   "recall": 0.11363636363636363,
   "f1-score": 0.18518518518518517,
   "support": 88.0
  },
  "26": {
   "precision": 0.5609756097560976,
   "recall": 0.7931034482758621,
   "f1-score": 0.6571428571428571,
   "support": 29.0
  },
  "27": {
   "precision": 0.22727272727272727,
   "recall": 0.20833333333333334,
   "f1-score": 0.21739130434782608,
   "support": 24.0
  },
  "28": {
   "precision": 0.5905511811023622,
   "recall": 0.7731958762886598,
   "f1-score": 0.6696428571428571,
   "support": 97.0
  },
  "29": {
   "precision": 0.10714285714285714,
   "recall": 0.5454545454545454,
   "f1-score": 0.1791044776119403,
   "support": 11.0
  },
  "30": {
   "precision": 0.47191011235955055,
   "recall": 0.47191011235955055,
   "f1-score": 0.47191011235955055,
   "support": 89.0
  },
  "31": {
   "precision": 0.35294117647058826,
   "recall": 0.75,
   "f1-score": 0.48,
   "support": 16.0
  },
  "accuracy": 0.4092186621697583,
  "macro avg": {
   "precision": 0.37517742934777787,
   "recall": 0.425469513236185,
   "f1-score": 0.37209566146448914,
   "support": 1779.0
  },
  "weighted avg": {
   "precision": 0.44626360499616513,
   "recall": 0.4092186621697583,
   "f1-score": 0.4030808644228083,
   "support": 1779.0
  }
 }
}