{
 "dataset": "segerstolpe",
 "n_samples": 2127,
 "n_features": 2000,
 "n_classes": 11,
 "cv_folds": 5,
 "transformer_params": 598400,
 "total_params": 928769,
 "config": {
  "heads": [
   "cell_type"
  ],
  "cohorts": null,
  "n_hvg": null,
  "n_channels": 1,
  "batch_size": 128,
  "val_frac": 0.15,
  "test_frac": 0.15,
  "d_model": 136,
  "n_heads": 4,
  "d_ff": 272,
  "dropout": 0.1,
  "n_markers": 128,
  "marker_mode": "router",
  "pathway_pool": "mean",
  "compress_mode": "aggregate",
  "recursive_marker_refine": true,
  "peak_init": true,
  "anneal_markers": true,
  "recursion_depth": 4,
  "share_weights": false,
  "share_strategy": "cycle",
  "n_unique_blocks": null,
  "step_cache": false,
  "adaptive_depth": false,
  "marker_ffn": false,
  "recursion_mode": "expert",
  "router_capacity": null,
  "router_alpha": 1.0,
  "router_temp": 1.0,
  "router_type": "linear",
  "router_z_coeff": 0.001,
  "router_balance_coeff": 0.1,
  "gene_interaction": "none",
  "interaction_knn": 16,
  "router_prior_beta": 1.0,
  "router_prior_anneal": true,
  "bio_graph_prop": false,
  "bio_prop_lambda_init": 0.3,
  "bio_prop_hops": 1,
  "bio_prior_gate": false,
  "bio_deconfound_pc": 0,
  "bio_precision": false,
  "bio_centrality": "eigcent",
  "bio_prior_learnable": false,
  "bio_beta_init": 0.5,
  "bio_depth_laplacian": 0.0,
  "bio_learned_graph": false,
  "bio_learned_rank": 16,
  "bio_learned_init": "random",
  "bio_learned_fuse": false,
  "bio_fuse_source": "coexpr",
  "aggnet_species": "human",
  "bio_learned_anchor": false,
  "bio_anchor_lambda": 0.5,
  "bio_anchor_floor": 0.0,
  "bio_anchor_rank": 16,
  "bio_anchor_source": "coexpr",
  "bio_init_scale": 0.05,
  "bio_init_rand": 0.005,
  "pathway_attn_bias": false,
  "pathway_attn_lambda": 2.0,
  "lambda_marker": 0.1,
  "gamma_diversity": 0.05,
  "beta_compression": 0.01,
  "lr": 0.001,
  "weight_decay": 1e-05,
  "epochs": 100,
  "patience": 15,
  "seed": 42,
  "device": "cuda"
 },
 "fold_metrics": [
  {
   "fold": 0,
   "n_test": 426,
   "accuracy": 0.8943661971830986,
   "macro_f1": 0.6922203193090977,
   "weighted_f1": 0.8955289421952745
  },
  {
   "fold": 1,
   "n_test": 426,
   "accuracy": 0.8262910798122066,
   "macro_f1": 0.7413760165795213,
   "weighted_f1": 0.832783006678876
  },
  {
   "fold": 2,
   "n_test": 425,
   "accuracy": 0.8823529411764706,
   "macro_f1": 0.7060329653481258,
   "weighted_f1": 0.8855621888919522
  },
  {
   "fold": 3,
   "n_test": 425,
   "accuracy": 0.8611764705882353,
   "macro_f1": 0.6089118909572337,
   "weighted_f1": 0.8617096065781042
  },
  {
   "fold": 4,
   "n_test": 425,
   "accuracy": 0.8094117647058824,
   "macro_f1": 0.7860355070224494,
   "weighted_f1": 0.8255911784584647
  }
 ],
 "accuracy": {
  "mean": 0.8547196906931788,
  "std": 0.03236703906641095
 },
 "macro_f1": {
  "mean": 0.7069153398432856,
  "std": 0.05876893278321304
 },
 "weighted_f1": {
  "mean": 0.8602349845605344,
  "std": 0.027724031545631227
 },
 "cv_macro_f1": {
  "mean": 70.69153398432856,
  "std": 5.876893278321304,
  "folds": [
   69.22203193090976,
   74.13760165795213,
   70.60329653481257,
   60.89118909572338,
   78.60355070224495
  ]
 }
}