{
 "family": "pnet",
 "cohort": "blca",
 "task": "response",
 "mode": "learned",
 "K": 4,
 "seed": 1,
 "test_macro_f1": 33.387259858442874,
 "test_accuracy": 33.60655737704918,
 "n_features": 3000,
 "n_classes": 2,
 "n_samples": 404,
 "learned_lambda": 0.20336894690990448,
 "learned_beta": 0.9740769863128662,
 "graph_diag": {
  "n_genes": 3000,
  "n_genes_in_reactome": 3000,
  "reactome_coverage_frac": 1.0,
  "mean_degree": 26.058666666666667,
  "isolated_frac": 0.0,
  "corr_pi_pc1": 0.023062359541654587
 }
}