{
 "task": "os_binary",
 "n_samples": 867,
 "n_genes": 20530,
 "n_classes": 2,
 "cv_folds": 5,
 "transformer_params": 132992,
 "total_params": 2827781,
 "config": {
  "heads": [
   "os_binary"
  ],
  "cohorts": null,
  "n_hvg": null,
  "batch_size": 32,
  "val_frac": 0.15,
  "test_frac": 0.15,
  "d_model": 128,
  "n_heads": 4,
  "d_ff": 256,
  "dropout": 0.1,
  "n_markers": 256,
  "marker_mode": "router",
  "compress_mode": "aggregate",
  "recursive_marker_refine": true,
  "peak_init": true,
  "anneal_markers": true,
  "recursion_depth": 4,
  "share_weights": true,
  "adaptive_depth": false,
  "marker_ffn": false,
  "recursion_mode": "token",
  "router_capacity": null,
  "router_alpha": 1.0,
  "router_temp": 1.0,
  "router_type": "linear",
  "router_z_coeff": 0.001,
  "router_balance_coeff": 0.1,
  "gene_interaction": "none",
  "interaction_knn": 16,
  "router_prior_beta": 1.0,
  "router_prior_anneal": true,
  "lambda_marker": 0.1,
  "gamma_diversity": 0.05,
  "beta_compression": 0.01,
  "lr": 0.0003,
  "weight_decay": 0.01,
  "epochs": 40,
  "patience": 8,
  "seed": 42,
  "device": "cuda"
 },
 "fold_metrics": [
  {
   "fold": 0,
   "n_test": 174,
   "accuracy": 0.6609195402298851,
   "macro_f1": 0.4282372598162072,
   "weighted_f1": 0.6127060947387627
  },
  {
   "fold": 1,
   "n_test": 174,
   "accuracy": 0.6436781609195402,
   "macro_f1": 0.5481655218629586,
   "weighted_f1": 0.6532294248251984
  },
  {
   "fold": 2,
   "n_test": 173,
   "accuracy": 0.4508670520231214,
   "macro_f1": 0.4381772809626363,
   "weighted_f1": 0.4806392072034902
  },
  {
   "fold": 3,
   "n_test": 173,
   "accuracy": 0.6184971098265896,
   "macro_f1": 0.5756021409455843,
   "weighted_f1": 0.6434541826300836
  },
  {
   "fold": 4,
   "n_test": 173,
   "accuracy": 0.6589595375722543,
   "macro_f1": 0.47723431498079383,
   "weighted_f1": 0.6322352401323337
  }
 ],
 "accuracy": {
  "mean": 0.6065842801142782,
  "std": 0.07932365941503558
 },
 "macro_f1": {
  "mean": 0.4934833037136361,
  "std": 0.058844677655156975
 },
 "weighted_f1": {
  "mean": 0.6044528299059737,
  "std": 0.06335622083319588
 }
}